{
  "tours": [
    {
      "id": "da-nang-4n3d-danang-bana-hoian-culaocham",
      "name": "Đà Nẵng 4N3D: Đà Nẵng-Bà Nà-Hội An-Cù Lao Chàm",
      "type": 0,
      "locationId": "da-nang",
      "locationName": "Đà Nẵng",
      "time": "4 Ngày 3 Đêm",
      "img": "/img/da-nang.jpg",
      "price": 2950000,
      "hot": 1,
      "destination": "Hà Nội, Đà Nẵng, Hội An",
      "vehicle": "ô tô, thuyền",
      "limitAge": "18-39",
      "maxGuest": 20,
      "accommodation": "Khách sạn 3 sao",
      "start": "Hà Nội, Thứ 3, thứ 5 hàng tuần"
    },
    {
      "id": "da-nang-3n2d-danang-bana-hoian-culaocham",
      "name": "Đà Nẵng 3N2D: Đà Nẵng-Bà Nà-Hội An-Cù Lao Chàm",
      "type": 0,
      "locationId": "da-nang",
      "locationName": "Đà Nẵng",
      "time": "3 Ngày 2 Đêm",
      "img": "/img/da-nang.jpg",
      "price": 2150000,
      "hot": 1,
      "destination": "Đà Nẵng, Hội An",
      "vehicle": "ô tô, thuyền",
      "limitAge": "18-39",
      "maxGuest": 20,
      "accommodation": "Khách sạn 3 sao",
      "start": "Đà Nẵng, Thứ 2, thứ 4 hàng tuần"
    },
    {
      "id": "da-nang-5n4d-danang-bana-hoian-culaocham",
      "name": "Đà Nẵng 5N4D: Đà Nẵng-Bà Nà-Hội An-Cù Lao Chàm",
      "type": 0,
      "locationId": "da-nang",
      "locationName": "Đà Nẵng",
      "time": "5 Ngày 4 Đêm",
      "img": "/img/da-nang.jpg",
      "price": 3550000,
      "hot": 1,
      "destination": "Hồ Chí Minh, Đà Nẵng, Hội An",
      "vehicle": "ô tô, thuyền",
      "limitAge": "18-39",
      "maxGuest": 20,
      "accommodation": "Khách sạn 3 sao",
      "start": "Hồ Chí Minh, Thứ 4, thứ 6 hàng tuần"
    },
    {
      "id": "thai-lan-4n3d-thien-duong-du-lich-PhuKet",
      "name": "Thái Lan 4N3D: Thiên đường du lịch PhuKet",
      "type": 1,
      "locationId": "thai-lan",
      "locationName": "Thái Lan",
      "time": "4 Ngày 3 Đêm",
      "img": "/img/thai-lan.jpg",
      "price": 7690000,
      "hot": 1,
      "destination": "Hồ Chí Minh, Thái Lan, PhuKet",
      "vehicle": "ô tô, máy bay",
      "limitAge": "18-39",
      "maxGuest": 20,
      "accommodation": "Khách sạn 3 sao",
      "start": "Hồ Chí Minh, Thứ 6 hàng tuần"
    },
    {
      "id": "thai-lan-5n4d-thien-duong-du-lich-PhuKet",
      "name": "Thái Lan 5N4D: Thiên đường du lịch PhuKet",
      "type": 1,
      "locationId": "thai-lan",
      "locationName": "Thái Lan",
      "time": "5 Ngày 4 Đêm",
      "img": "/img/thai-lan.jpg",
      "price": 9690000,
      "hot": 1,
      "destination": "Hà Nội, Thái Lan, PhuKet",
      "vehicle": "ô tô, máy bay",
      "limitAge": "18-39",
      "maxGuest": 20,
      "accommodation": "Khách sạn 3 sao",
      "start": "Hà Nội, Thứ 5 hàng tuần"
    },
    {
      "id": "thai-lan-9n8d-thien-duong-du-lich-PhuKet",
      "name": "Thái Lan 9N8D: Thiên đường du lịch PhuKet",
      "type": 1,
      "locationId": "thai-lan",
      "locationName": "Thái Lan",
      "time": "9 Ngày 8 Đêm",
      "img": "/img/thai-lan.jpg",
      "price": 15690000,
      "hot": 1,
      "destination": "Đà Nẵng, Thái Lan, PhuKet",
      "vehicle": "ô tô, máy bay",
      "limitAge": "18-39",
      "maxGuest": 20,
      "accommodation": "Khách sạn 3 sao",
      "start": "Đà Nẵng, Thứ 5 hàng tuần"
    }
  ],
  "comments": [
    {
      "idTour": "da-nang-4-ngay-3-dem",
      "name": "Tuấn",
      "time": "15/8/2018  18:41:9",
      "cmt": "Đẹp quá!",
      "id": 1
    },
    {
      "idTour": "da-nang-5-ngay-4-dem",
      "name": "Tuấn",
      "time": "15/8/2018  18:41:9",
      "cmt": "Đẹp quá!",
      "id": 2
    },
    {
      "idTour": "da-nang-4-ngay-3-dem",
      "name": "Lộc",
      "time": "9/10/2018  17:37:14",
      "cmt": "Ha ha ha ha ha ha !!!",
      "id": 3
    },
    {
      "idTour": "da-nang-9-ngay-4-dem",
      "name": "Lộc",
      "time": "9/10/2018  19:16:52",
      "cmt": "Tour này tốt, giá rẻ.",
      "id": 4
    },
    {
      "idTour": "da-nang-4-ngay-3-dem",
      "name": "hh",
      "time": "10/10/2018  9:39:24",
      "cmt": "jgh",
      "id": 5
    },
    {
      "idTour": "da-nang-4n3d-danang-bana-hoian-culaocham",
      "name": "Chiến",
      "time": "11/10/2018  9:6:47",
      "cmt": "Tour rẻ quá!",
      "id": 6
    }
  ],
  "places": [
    {
      "id": "ha-noi",
      "name": "Hà Nội",
      "type": 0
    },
    {
      "id": "ho-chi-minh",
      "name": "Hồ Chí Minh",
      "type": 0
    },
    {
      "id": "da-nang",
      "name": "Đà Nẵng",
      "type": 0
    },
    {
      "id": "ha-long",
      "name": "Hạ Long",
      "type": 0
    },
    {
      "id": "nha-trang",
      "name": "Nha Trang",
      "type": 0
    },
    {
      "id": "da-lat",
      "name": "Đà Lạt",
      "type": 0
    },
    {
      "id": "mien-tay",
      "name": "Miền Tây",
      "type": 0
    },
    {
      "id": "quang-binh",
      "name": "Quảng Bình",
      "type": 0
    },
    {
      "id": "con-dao",
      "name": "Côn Đảo",
      "type": 0
    },
    {
      "id": "trung-quoc",
      "name": "Trung Quốc",
      "type": 1
    },
    {
      "id": "thai-lan",
      "name": "Thái Lan",
      "type": 1
    },
    {
      "id": "dai-loan",
      "name": "Đài Loan",
      "type": 1
    },
    {
      "id": "hong-kong",
      "name": "Hồng Kông",
      "type": 1
    },
    {
      "id": "singapore",
      "name": "Singapore",
      "type": 1
    },
    {
      "id": "han-quoc",
      "name": "Hàn Quốc",
      "type": 1
    },
    {
      "id": "nhat-ban",
      "name": "Nhật Bản",
      "type": 1
    },
    {
      "id": "campuchia",
      "name": "Campuchia",
      "type": 1
    },
    {
      "id": "indonesia",
      "name": "Indonesia",
      "type": 1
    },
    {
      "id": "malaysia",
      "name": "Malaysia",
      "type": 1
    },
    {
      "id": "chau-au",
      "name": "Châu Âu",
      "type": 1
    },
    {
      "id": "usa",
      "name": "Mỹ",
      "type": 1
    },
    {
      "id": "canada",
      "name": "Canada",
      "type": 1
    }
  ],
  "users": [
    {
      "id": 1,
      "userName": "lebathanhtuan",
      "password": "123321",
      "fullName": "Lê Bá Thanh Tuấn",
      "email": "lebathanhtuan@gmail.com"
    },
    {
      "id": 2,
      "userName": "lbttuan",
      "password": "123321",
      "fullName": "Lê Bá Thanh Tuấn",
      "email": "lebathanhtuan@gmail.com"
    },
    {
      "id": 3,
      "userName": "lbttuan1",
      "password": "123321",
      "fullName": "Lê Bá Thanh Tuấn",
      "email": "lebathanhtuan@gmail.com"
    },
    {
      "userName": "lbttuan2",
      "password": "123321",
      "fullName": "Lê Bá Thanh Tuấn",
      "email": "lebathanhtuan2@gmail.com",
      "id": 4
    }
  ],
  "historyBookTour": [
    {
      "idTour": "da-nang-4-ngay-3-dem",
      "userName": "lebathanhtuan",
      "timeTour": "18/10/2018",
      "guest": 2,
      "price": 4200000,
      "timeBook": "10/10/2018  23:23:12",
      "id": 1
    },
    {
      "idTour": "da-nang-5-ngay-4-dem",
      "userName": "lebathanhtuan",
      "timeTour": "25/10/2018",
      "guest": 3,
      "price": 4200000,
      "timeBook": "10/10/2018  23:23:12",
      "id": 2
    },
    {
      "idTour": "da-nang-9-ngay-4-dem",
      "userName": "lbttuan",
      "timeTour": "31/10/2018",
      "guest": 2,
      "price": 4200000,
      "timeBook": "11/10/2018  1:4:33",
      "id": 3
    },
    {
      "idTour": "da-nang-4n3d-danang-bana-hoian-culaocham",
      "userName": "lebathanhtuan",
      "timeTour": "13/10/2018",
      "guest": 7,
      "price": 2950000,
      "timeBook": "11/10/2018  9:8:54",
      "id": 4
    },
    {
      "idTour": "thai-lan-4n3d-thien-duong-du-lich-PhuKet",
      "userName": "lebathanhtuan",
      "timeTour": "27/10/2018",
      "guest": 3,
      "price": 7690000,
      "timeBook": "11/10/2018  9:8:54",
      "id": 5
    }
  ]
}